tqwgp_parser/__init__.py
tqwgp_parser/__main__.py
tqwgp_parser/constants.py
tqwgp_parser/parser.hy
tqwgp_parser/utils.hy
tqwgp_parser/files/loaders.py
tqwgp_parser-0.8.1.data/scripts/tqwgp
tqwgp_parser-0.8.1.dist-info/licenses/LICENSE
tqwgp_parser-0.8.1.dist-info/METADATA
tqwgp_parser-0.8.1.dist-info/WHEEL
tqwgp_parser-0.8.1.dist-info/top_level.txt
tqwgp_parser-0.8.1.dist-info/RECORD
