Metadata-Version: 2.4
Name: tqwgp-parser
Version: 0.8.1
Summary: A library for parsing Talk Quote Work Get-Paid (TQWGP) text-based compliant sales and accounting documents.
Home-page: https://github.com/YtoTech/talk-quote-work-getpaid-parser
Author: Yoan Tournade
Author-email: y@yoantournade.com
License: AGPL-3.0
Platform: any
License-File: LICENSE
Requires-Dist: hy>=0.26.0
Requires-Dist: toolz
Requires-Dist: pendulum
Requires-Dist: toml
Requires-Dist: pyyaml
Requires-Dist: click
Requires-Dist: babel
Dynamic: author
Dynamic: author-email
Dynamic: description
Dynamic: description-content-type
Dynamic: home-page
Dynamic: license
Dynamic: license-file
Dynamic: platform
Dynamic: requires-dist
Dynamic: summary
